{
  "pages": [
    {
      "name": "Home",
      "path": "/test/home",
      "version": "0.1.0",
      "lastUpdated": "2025-09-26T00:00:00.000Z",
      "description": "Site homepage rendered from JSON.",
      "sections": [
        { "type": "hero", "props": { "title": "Backslash Designs", "subtitle": "Scalable | Reliable | Secure" } },
        {
          "type": "section",
          "props": {
            "id": "Sectors",
            "title": "Our Sectors",
            "sections": [
              {
                "type": "columns",
                "props": {
                  "gap": 2,
                  "itemSpacing": 1.25,
                  "withCards": false,
                  "columns": [
                    [
                      {
                        "type": "card",
                        "props": {
                          "title": "Live Broadcast & Pro A/V",
                          "iconName": "Videocam",
                          "subtitle": "Live event production, streaming, and broadcast solutions.",
                          "elevation": 1,
                          "actions": [
                            { "label": "Learn more", "to": "/sectors#broadcast", "size": "small" }
                          ]
                        }
                      }
                    ],
                    [
                      {
                        "type": "card",
                        "props": {
                          "title": "Mental Health & Clinical Practices",
                          "iconName": "LocalHospital",
                          "subtitle": "Clinical IT, charting, and secure workflows for practices.",
                          "actions": [
                            { "label": "Learn more", "to": "/sectors#mental-health", "size": "small" }
                          ]
                        }
                      }
                    ],
                    [
                      {
                        "type": "card",
                        "props": {
                          "title": "Non-Profit Organizations",
                          "iconName": "VolunteerActivism",
                          "subtitle": "Affordable, mission-driven IT for non-profits and charities.",
                          "actions": [
                            { "label": "Learn more", "to": "/sectors#non-profit", "size": "small" }
                          ]
                        }
                      }
                    ]
                  ]
                }
              }
            ]
          }
        },
        {
          "type": "section",
          "props": {
            "id": "Features",
            "title": "Features",
            "subtitle": "What this demo includes",
            
            "sections": [
              { "type": "text", "props": { "body": "- Multiple routes defined in JSON\n- Anchorable container sections\n- Columns with cards and CTAs\n- Consistent in-place editing flags" } }
            ]
          }
        },
        {
          "type": "columns",
          "props": {
            "title": "Quick Links",
            "gap": 2,
            "itemSpacing": 1.25,
            "withCards": true,
            "columns": [
              [
                { "type": "hero", "props": { "title": "Dynamic Pages", "subtitle": "Browse the dynamic demo pages." } },
                { "type": "button", "props": { "label": "Dynamic", "to": "/test/dynamic", "variant": "outlined", "size": "small" } }
              ],
              [
                { "type": "hero", "props": { "title": "Services", "subtitle": "See what we offer." } },
                { "type": "button", "props": { "label": "Services", "to": "/test/services", "variant": "outlined", "size": "small" } }
              ],
              [
                { "type": "hero", "props": { "title": "About", "subtitle": "Learn more about us." } },
                { "type": "button", "props": { "label": "About", "to": "/test/about", "variant": "outlined", "size": "small" } }
              ]
            ]
          }
        },
        {
          "type": "section",
          "props": {
            "id": "GetStarted",
            "title": "Get Started",
            "subtitle": "Jump into the examples below.",
            "sections": [
              { "type": "text", "props": { "body": "Use the buttons above to navigate. Each page demonstrates different section types." } },
              { "type": "button", "props": { "label": "Learn About Us", "to": "/about#Team", "variant": "outlined", "size": "small" } }
            ]
          }
        }
      ]
    },

    {
      "name": "Services",
      "path": "/test/services",
      "version": "0.1.0",
      "lastUpdated": "2025-09-26T00:00:00.000Z",
      "description": "Services we provide.",
      "sections": [
        { "type": "hero", "props": { "title": "Services", "subtitle": "What we can do for you." } },
        { "type": "text", "props": { "body": "Explore a few sample service offerings laid out using sections and columns." } },
        {
          "type": "section",
          "props": {
            "id": "Offerings",
            "title": "Offerings",
            "subtitle": "Three example services.",
            "sections": [
              {
                "type": "columns",
                "props": {
                  "title": "Service Cards",
                  "gap": 2,
                  "itemSpacing": 1.25,
                  "withCards": true,
                  "columns": [
                    [
                      { "type": "hero", "props": { "title": "Design", "subtitle": "UI/UX, branding, and design systems." } },
                      { "type": "button", "props": { "label": "Request Design", "to": "/test/services#Offerings", "variant": "outlined", "size": "small" } }
                    ],
                    [
                      { "type": "hero", "props": { "title": "Development", "subtitle": "Web apps, static sites, and APIs." } },
                      { "type": "button", "props": { "label": "Request Dev", "to": "/test/services#Offerings", "variant": "outlined", "size": "small" } }
                    ],
                    [
                      { "type": "hero", "props": { "title": "Consulting", "subtitle": "Architecture, audits, and guidance." } },
                      { "type": "button", "props": { "label": "Request Consult", "to": "/test/services#Offerings", "variant": "outlined", "size": "small" } }
                    ]
                  ]
                }
              }
            ]
          }
        },
        {
          "type": "section",
          "props": {
            "id": "WhyUs",
            "title": "Why Choose Us",
            "subtitle": "What makes this stack useful.",
            
            "sections": [
              { "type": "text", "props": { "body": "- JSON-driven layout for rapid iteration\n- Reusable components mapped by type\n- Easy to extend with new section types later" } }
            ]
          }
        },
        {
          "type": "columns",
          "props": {
            "title": "Navigate",
            "gap": 2,
            "itemSpacing": 1.25,
            "withCards": true,
            "columns": [
              [
                { "type": "hero", "props": { "title": "Home", "subtitle": "Back to the start." } },
                { "type": "button", "props": { "label": "Home", "to": "/test/home", "variant": "outlined", "size": "small" } }
              ],
              [
                { "type": "hero", "props": { "title": "Dynamic Alt", "subtitle": "Another dynamic page." } },
                { "type": "button", "props": { "label": "Dynamic Alt", "to": "/test/about", "variant": "outlined", "size": "small" } }
              ],
              [
                { "type": "hero", "props": { "title": "About", "subtitle": "Learn more." } },
                { "type": "button", "props": { "label": "About", "to": "/test/about", "variant": "outlined", "size": "small" } }
              ]
            ]
          }
        }
      ]
    },

    {
      "name": "About",
      "path": "/test/about",
      "version": "0.1.0",
      "lastUpdated": "2025-09-26T00:00:00.000Z",
      "description": "About this project.",
      "sections": [
        { "type": "hero", "props": { "title": "About", "subtitle": "A bit of background." } },
        { "type": "text", "props": { "body": "This demo shows how pages, sections, and content can be configured via JSON to power a small site." } },
        {
          "type": "section",
          "props": {
            "id": "Mission",
            "title": "Mission",
            "subtitle": "Why this exists.",
            
            "sections": [
              { "type": "text", "props": { "body": "Enable non-developers to iterate on content structure rapidly, while developers maintain a clean component library." } }
            ]
          }
        },
        {
          "type": "section",
          "props": {
            "id": "Team",
            "title": "Team",
            "subtitle": "People behind the project.",
            
            "sections": [
              {
                "type": "columns",
                "props": {
                  "title": "Team Cards",
                  "gap": 2,
                  "itemSpacing": 1.25,
                  "withCards": true,
                  "columns": [
                    [
                      { "type": "hero", "props": { "title": "Dev", "subtitle": "Builds components." } },
                      { "type": "text", "props": { "body": "Focus: React, routing, and dynamic rendering." } }
                    ],
                    [
                      { "type": "hero", "props": { "title": "Designer", "subtitle": "Crafts experience." } },
                      { "type": "text", "props": { "body": "Focus: UX, accessibility, and aesthetics." } }
                    ],
                    [
                      { "type": "hero", "props": { "title": "Editor", "subtitle": "Maintains content." } },
                      { "type": "text", "props": { "body": "Focus: Structure, clarity, and accuracy." } }
                    ]
                  ]
                }
              }
            ]
          }
        },
        {
          "type": "columns",
          "props": {
            "title": "More",
            "gap": 2,
            "itemSpacing": 1.25,
            "withCards": true,
            "columns": [
              [
                { "type": "hero", "props": { "title": "Home", "subtitle": "Go back home." } },
                { "type": "button", "props": { "label": "Home", "to": "/test/home", "variant": "outlined", "size": "small" } }
              ],
              [
                { "type": "hero", "props": { "title": "Services", "subtitle": "See services." } },
                { "type": "button", "props": { "label": "Services", "to": "/test/services", "variant": "outlined", "size": "small" } }
              ],
              [
                { "type": "hero", "props": { "title": "Dynamic", "subtitle": "Demo page." } },
                { "type": "button", "props": { "label": "Dynamic", "to": "/test/dynamic", "variant": "outlined", "size": "small" } }
              ]
            ]
          }
        }
      ]
    }
  ]
}